pyap/__init__.py
pyap/address.py
pyap/api.py
pyap/exceptions.py
pyap/packages/__init__.py
pyap/packages/six.py
pyap/parser.py
pyap/source_CA/__init__.py
pyap/source_CA/data.py
pyap/source_GB/__init__.py
pyap/source_GB/data.py
pyap/source_US/__init__.py
pyap/source_US/data.py
pyap/utils.py
pyap-0.3.0.dist-info/LICENSE
pyap-0.3.0.dist-info/WHEEL
pyap-0.3.0.dist-info/METADATA
pyap-0.3.0.dist-info/RECORD
